dasl_client/__init__.py
dasl_client/client.py
dasl_client/exec_rule.py
dasl_client/helpers.py
dasl_client/metadata.py
dasl_client/regions.json
dasl_client/regions.py
dasl_client/auth/__init__.py
dasl_client/auth/auth.py
dasl_client/conn/__init__.py
dasl_client/conn/client_identifier.py
dasl_client/conn/conn.py
dasl_client/errors/__init__.py
dasl_client/errors/errors.py
dasl_client/preset_development/__init__.py
dasl_client/preset_development/errors.py
dasl_client/preset_development/preview_engine.py
dasl_client/preset_development/preview_parameters.py
dasl_client/preset_development/stage.py
dasl_client/types/__init__.py
dasl_client/types/admin_config.py
dasl_client/types/content.py
dasl_client/types/datasource.py
dasl_client/types/dbui.py
dasl_client/types/helpers.py
dasl_client/types/rule.py
dasl_client/types/types.py
dasl_client/types/workspace_config.py
dasl_client-1.0.34.dist-info/licenses/LICENSE
dasl_client-1.0.34.dist-info/METADATA
dasl_client-1.0.34.dist-info/WHEEL
dasl_client-1.0.34.dist-info/top_level.txt
dasl_client-1.0.34.dist-info/RECORD
