Metadata-Version: 2.4
Name: dasl_client
Version: 1.0.34
Summary: The DASL client library used for interacting with the DASL workspace
Author-email: Antimatter Team <support@antimatter.io>
Requires-Python: >=3.8
License-File: LICENSE
Requires-Dist: dasl_api==0.1.30
Requires-Dist: databricks-sdk>=0.41.0
Requires-Dist: pydantic>=2
Requires-Dist: typing_extensions>=4.10.0
Requires-Dist: pyyaml==6.0.2
Dynamic: license-file
